{"http://archaeology.link/ontology#3dmodel": ["http://data.archaeology.link/data/ars/ic_b8ff417b-d71c-4765-b355-4f1cb308d769_3dmodel"], "http://archaeology.link/ontology#arachneEntityID": ["http://arachne.dainst.org/entity/7031585"], "http://archaeology.link/ontology#arachneModelID": ["http://arachne.dainst.org/entity/7031586"], "http://archaeology.link/ontology#carries": ["http://data.archaeology.link/data/ars/feat_6f34eb25-0c97-41c0-902b-9503d4f2cb44", "http://data.archaeology.link/data/ars/feat_a5a386d1-d181-4294-8bf0-5b333be19543", "http://data.archaeology.link/data/ars/feat_d367fc77-c753-4610-a53c-4830f1ab5387"], "http://archaeology.link/ontology#inventoryNumber": ["O.40754 (RGZM)"], "http://archaeology.link/ontology#madeBy": ["http://data.archaeology.link/data/ars/mould_made"], "http://archaeology.link/ontology#number": ["1"], "http://purl.org/dc/elements/1.1/identifier": ["b8ff417b-d71c-4765-b355-4f1cb308d769"], "http://rdfs.org/ns/void#inDataset": ["http://data.archaeology.link/data/ars/ars_dataset"], "http://www.cidoc-crm.org/cidoc-crm/P41_classified": ["http://data.archaeology.link/data/ars/lamp"], "http://www.cidoc-crm.org/cidoc-crm/P44_has_condition": ["http://data.archaeology.link/data/ars/completeCondition"], "http://www.cidoc-crm.org/cidoc-crm/P45_consists_of": ["http://data.archaeology.link/data/ars/clay"], "http://www.w3.org/1999/02/22-rdf-syntax-ns#type": ["http://archaeology.link/ontology#ARS_Object"], "http://www.w3.org/2000/01/rdf-schema#label": ["lamp with men and animal"], "http://www.w3.org/ns/prov-o/wasAttributedTo": ["http://data.archaeology.link/data/ars/ImportPythonScript_ARS3D"], "http://www.w3.org/ns/prov-o/wasDerivedFrom": ["http://www.wikidata.org/entity/Q105268778"], "http://www.w3.org/ns/prov-o/wasGeneratedBy": ["http://data.archaeology.link/data/ars/activity_ic_b8ff417b-d71c-4765-b355-4f1cb308d769"], "http://xmlns.com/foaf/0.1/image": ["https://zenodo.org/record/5645180/files/b8ff417b-d71c-4765-b355-4f1cb308d769.jpg"]}